li_api/__init__.py
li_api/lib.py
rmsliapi-0.0.3.dist-info/METADATA
rmsliapi-0.0.3.dist-info/WHEEL
rmsliapi-0.0.3.dist-info/top_level.txt
rmsliapi-0.0.3.dist-info/RECORD
