Metadata-Version: 2.1
Name: rmsliapi
Version: 0.0.3
Summary: Python Client to geocode using the LI API
Home-page: https://github.com/RMS/GMD/li-clients/li_api_python_client
Author: Daniel Fox
Author-email: dfox@rms.com
Classifier: Programming Language :: Python :: 3
Classifier: License :: OSI Approved :: MIT License
Classifier: Operating System :: OS Independent
Requires-Python: >=3.10
